LICENSE.txt
MANIFEST.in
README.md
setup.cfg
setup.py
DmpTools/DmpTools.py
DmpTools/StreamlitServerrun.py
DmpTools/__init__.py
DmpTools/app_setting.py
DmpTools/browser_manager.py
DmpTools/custom_key_event.py
DmpTools/custom_key_event3.py
DmpTools/custom_key_event4.py
DmpTools/快捷键列表.xlsx
DmpTools.egg-info/PKG-INFO
DmpTools.egg-info/SOURCES.txt
DmpTools.egg-info/dependency_links.txt
DmpTools.egg-info/top_level.txt
DmpTools/icons/Forword_picture.png
DmpTools/icons/__init__.py
DmpTools/icons/back_picture.png
DmpTools/icons/home.png
DmpTools/icons/logo.png
DmpTools/icons/refresh.png
DmpTools/icons/stop.png